odoo/addons/mrp_attachment_mgmt/README.rst
odoo/addons/mrp_attachment_mgmt/__init__.py
odoo/addons/mrp_attachment_mgmt/__manifest__.py
odoo/addons/mrp_attachment_mgmt/i18n/es.po
odoo/addons/mrp_attachment_mgmt/i18n/it.po
odoo/addons/mrp_attachment_mgmt/i18n/mrp_attachment_mgmt.pot
odoo/addons/mrp_attachment_mgmt/models/__init__.py
odoo/addons/mrp_attachment_mgmt/models/mrp_bom.py
odoo/addons/mrp_attachment_mgmt/models/mrp_production.py
odoo/addons/mrp_attachment_mgmt/models/mrp_workorder.py
odoo/addons/mrp_attachment_mgmt/models/product.py
odoo/addons/mrp_attachment_mgmt/readme/CONFIGURE.rst
odoo/addons/mrp_attachment_mgmt/readme/CONTRIBUTORS.rst
odoo/addons/mrp_attachment_mgmt/readme/DESCRIPTION.rst
odoo/addons/mrp_attachment_mgmt/readme/USAGE.rst
odoo/addons/mrp_attachment_mgmt/static/description/icon.png
odoo/addons/mrp_attachment_mgmt/static/description/index.html
odoo/addons/mrp_attachment_mgmt/tests/__init__.py
odoo/addons/mrp_attachment_mgmt/tests/common.py
odoo/addons/mrp_attachment_mgmt/tests/test_mrp_attachment_mgmt.py
odoo/addons/mrp_attachment_mgmt/views/mrp_bom_view.xml
odoo/addons/mrp_attachment_mgmt/views/mrp_production_views.xml
odoo/addons/mrp_attachment_mgmt/views/product_views.xml
odoo/addons/mrp_attachment_mgmt/views/workorder_attachments_views.xml
odoo14_addon_mrp_attachment_mgmt-14.0.1.3.0.dist-info/METADATA
odoo14_addon_mrp_attachment_mgmt-14.0.1.3.0.dist-info/WHEEL
odoo14_addon_mrp_attachment_mgmt-14.0.1.3.0.dist-info/top_level.txt
odoo14_addon_mrp_attachment_mgmt-14.0.1.3.0.dist-info/RECORD
